airflow_diagrams/__init__.py
airflow_diagrams/__main__.py
airflow_diagrams/abbreviations.yml
airflow_diagrams/airflow.py
airflow_diagrams/class_ref.py
airflow_diagrams/cli.py
airflow_diagrams/diagram.jinja2
airflow_diagrams/diagrams.py
airflow_diagrams/utils.py
airflow_diagrams-2.1.0.dist-info/entry_points.txt
airflow_diagrams-2.1.0.dist-info/LICENSE
airflow_diagrams-2.1.0.dist-info/WHEEL
airflow_diagrams-2.1.0.dist-info/METADATA
airflow_diagrams-2.1.0.dist-info/RECORD
