Metadata-Version: 2.1
Name: airflow-diagrams
Version: 2.1.0
Summary: Auto-generated Diagrams from Airflow DAGs.
License: Apache-2.0
Keywords: airflow,diagrams,cli
Author: Felix Uellendall
Author-email: feluelle@pm.me
Requires-Python: >=3.9,<4.0
Classifier: License :: OSI Approved :: Apache Software License
Classifier: Programming Language :: Python :: 3
Classifier: Programming Language :: Python :: 3.10
Classifier: Programming Language :: Python :: 3.9
Requires-Dist: PyYAML (>=6.0,<7.0)
Requires-Dist: apache-airflow-client (>=2.2.0,<3.0.0)
Requires-Dist: diagrams (>=0.21.0,<0.22.0)
Requires-Dist: fs (>=2.4.15,<3.0.0)
Requires-Dist: thefuzz[speedup] (>=0.19.0,<0.20.0)
Requires-Dist: typer[all] (>=0.6.1,<0.7.0)
